sound_arcanum/__init__.py
sound_arcanum/arcanum.py
sound_arcanum/base/__init__.py
sound_arcanum/base/player.py
sound_arcanum/base/plugin_lib.py
sound_arcanum/base/signal.py
sound_arcanum/base/utils.py
sound_arcanum/effects/__init__.py
sound_arcanum/effects/effect.py
sound_arcanum/effects/lib/__init__.py
sound_arcanum/effects/lib/common.py
sound_arcanum/effects/lib/convolution.py
sound_arcanum/effects/lib/impulse_response.py
sound_arcanum/effects/lib/modulation.py
sound_arcanum/effects/lib/stereo.py
sound_arcanum/generators/__init__.py
sound_arcanum/generators/generator.py
sound_arcanum/generators/lib/__init__.py
sound_arcanum/generators/lib/complex.py
sound_arcanum/generators/lib/drums.py
sound_arcanum/generators/lib/waves.py
sound_arcanum/gui/__init__.py
sound_arcanum/gui/main.py
sound_arcanum/gui/messages_from_dead.py
sound_arcanum/gui/port_dialog.py
sound_arcanum/gui/preset_dialog.py
sound_arcanum/gui/save_wav.py
sound_arcanum/gui/styles.css
sound_arcanum-0.1.3.dist-info/LICENSE
sound_arcanum-0.1.3.dist-info/METADATA
sound_arcanum-0.1.3.dist-info/WHEEL
sound_arcanum-0.1.3.dist-info/RECORD
