Metadata-Version: 2.3
Name: sound_arcanum
Version: 0.1.3
Summary: A package for doing great things!
License: MIT
Author: Dylan Garrett
Requires-Python: >=3.11,<4.0
Classifier: License :: OSI Approved :: MIT License
Classifier: Programming Language :: Python :: 3
Classifier: Programming Language :: Python :: 3.11
Classifier: Programming Language :: Python :: 3.12
Classifier: Programming Language :: Python :: 3.13
Requires-Dist: inquirerpy (>=0.3.4,<0.4.0)
Requires-Dist: mido (>=1.3.3,<2.0.0)
Requires-Dist: numpy (>=2.3.2,<3.0.0)
Requires-Dist: pynput (>=1.8.1,<2.0.0)
Requires-Dist: pyqt5 (>=5.15.11,<6.0.0)
Requires-Dist: scipy (>=1.16.1,<2.0.0)
Requires-Dist: sounddevice (>=0.5.2,<0.6.0)
